orgnet/__init__.py
orgnet/config.py
orgnet/core.py
orgnet/api/__init__.py
orgnet/api/app.py
orgnet/data/__init__.py
orgnet/data/ingestion.py
orgnet/data/models.py
orgnet/data/processors.py
orgnet/graph/__init__.py
orgnet/graph/builder.py
orgnet/graph/temporal.py
orgnet/graph/weights.py
orgnet/insights/__init__.py
orgnet/insights/ego_networks.py
orgnet/insights/executive.py
orgnet/insights/interventions.py
orgnet/insights/team_stability.py
orgnet/insights/validation.py
orgnet/metrics/__init__.py
orgnet/metrics/anomaly.py
orgnet/metrics/bonding_bridging.py
orgnet/metrics/centrality.py
orgnet/metrics/community.py
orgnet/metrics/structural.py
orgnet/metrics/utils.py
orgnet/ml/__init__.py
orgnet/ml/benchmarks.py
orgnet/ml/classification.py
orgnet/ml/classification_wrapper.py
orgnet/ml/embeddings.py
orgnet/ml/gnn.py
orgnet/ml/link_prediction.py
orgnet/nlp/__init__.py
orgnet/nlp/entities.py
orgnet/nlp/expertise.py
orgnet/nlp/sentiment.py
orgnet/nlp/topics.py
orgnet/predictive/__init__.py
orgnet/predictive/escalation.py
orgnet/predictive/response_time.py
orgnet/predictive/volume_forecast.py
orgnet/survival/__init__.py
orgnet/survival/discrete.py
orgnet/survival/models.py
orgnet/temporal/__init__.py
orgnet/temporal/change_detection.py
orgnet/temporal/cross_team_density.py
orgnet/temporal/new_hire_integration.py
orgnet/temporal/onboarding.py
orgnet/temporal/ts2net.py
orgnet/utils/__init__.py
orgnet/utils/audit.py
orgnet/utils/logging.py
orgnet/utils/performance.py
orgnet/utils/privacy.py
orgnet/visualization/__init__.py
orgnet/visualization/dashboard_html.py
orgnet/visualization/dashboards.py
orgnet/visualization/network.py
orgnet-0.1.2.dist-info/licenses/LICENSE
orgnet-0.1.2.dist-info/METADATA
orgnet-0.1.2.dist-info/WHEEL
orgnet-0.1.2.dist-info/entry_points.txt
orgnet-0.1.2.dist-info/top_level.txt
orgnet-0.1.2.dist-info/RECORD
