Metadata-Version: 2.4
Name: orgnet
Version: 0.1.2
Summary: Organizational Network Analysis Platform using ML and Graph Analytics
Home-page: https://github.com/kylejones200/orgnet
Author: Kyle Jones
Author-email: 
Maintainer: Kyle Jones
License: MIT
Project-URL: Homepage, https://github.com/kylejones200/orgnet
Project-URL: Documentation, https://github.com/kylejones200/orgnet#readme
Project-URL: Repository, https://github.com/kylejones200/orgnet
Project-URL: Issues, https://github.com/kylejones200/orgnet/issues
Keywords: organizational-network-analysis,network-analysis,graph-analytics,machine-learning,social-network-analysis,organizational-behavior,collaboration-analysis
Classifier: Development Status :: 4 - Beta
Classifier: Intended Audience :: Science/Research
Classifier: Intended Audience :: Developers
Classifier: Topic :: Scientific/Engineering :: Artificial Intelligence
Classifier: Topic :: Scientific/Engineering :: Information Analysis
Classifier: License :: OSI Approved :: MIT License
Classifier: Programming Language :: Python :: 3
Classifier: Programming Language :: Python :: 3.11
Classifier: Programming Language :: Python :: 3.12
Classifier: Operating System :: OS Independent
Requires-Python: >=3.11
License-File: LICENSE
Requires-Dist: numpy>=1.24.0
Requires-Dist: pandas>=2.0.0
Requires-Dist: networkx>=3.1
Requires-Dist: scipy>=1.10.0
Requires-Dist: scikit-learn>=1.3.0
Requires-Dist: python-dateutil>=2.8.2
Requires-Dist: pytz>=2023.3
Requires-Dist: pyyaml>=6.0
Requires-Dist: tqdm>=4.65.0
Requires-Dist: joblib>=1.3.0
Provides-Extra: graph
Requires-Dist: python-igraph>=0.10.0; extra == "graph"
Requires-Dist: node2vec>=0.4.6; extra == "graph"
Provides-Extra: ml
Requires-Dist: torch>=2.0.0; extra == "ml"
Requires-Dist: torch-geometric>=2.3.0; extra == "ml"
Requires-Dist: transformers>=4.30.0; extra == "ml"
Requires-Dist: sentence-transformers>=2.2.0; extra == "ml"
Provides-Extra: nlp
Requires-Dist: nltk>=3.8.1; extra == "nlp"
Requires-Dist: spacy>=3.5.0; extra == "nlp"
Requires-Dist: bertopic>=0.15.0; extra == "nlp"
Requires-Dist: gensim>=4.3.0; extra == "nlp"
Provides-Extra: viz
Requires-Dist: matplotlib>=3.7.0; extra == "viz"
Requires-Dist: seaborn>=0.12.0; extra == "viz"
Requires-Dist: plotly>=5.14.0; extra == "viz"
Requires-Dist: pyvis>=0.3.2; extra == "viz"
Requires-Dist: dash>=2.10.0; extra == "viz"
Requires-Dist: dash-bootstrap-components>=1.4.0; extra == "viz"
Provides-Extra: temporal
Requires-Dist: ruptures>=1.1.8; extra == "temporal"
Provides-Extra: api
Requires-Dist: flask>=2.3.0; extra == "api"
Requires-Dist: flask-cors>=4.0.0; extra == "api"
Requires-Dist: gunicorn>=21.0.0; extra == "api"
Provides-Extra: dev
Requires-Dist: pytest>=7.0.0; extra == "dev"
Requires-Dist: pytest-cov>=4.0.0; extra == "dev"
Requires-Dist: black>=23.0.0; extra == "dev"
Requires-Dist: flake8>=6.0.0; extra == "dev"
Provides-Extra: docs
Requires-Dist: sphinx>=5.0.0; extra == "docs"
Requires-Dist: sphinx-rtd-theme>=1.2.0; extra == "docs"
Requires-Dist: myst-parser>=1.0.0; extra == "docs"
Provides-Extra: all
Requires-Dist: orgnet[api,graph,ml,nlp,temporal,viz]; extra == "all"
Dynamic: home-page
Dynamic: license-file
Dynamic: requires-python
